sqle/__init__.py
sqle/adapter.py
sqle/contrib/__init__.py
sqle/contrib/class_property.py
sqle/contrib/text.py
sqle/exceptions.py
sqle/query.py
sqle/settings.py
sqle/sql.py
sqle/sqle-sqlite.code-workspace
sqle-0.0.0a3.dist-info/LICENSE
sqle-0.0.0a3.dist-info/METADATA
sqle-0.0.0a3.dist-info/WHEEL
sqle-0.0.0a3.dist-info/RECORD
