Metadata-Version: 2.1
Name: sqle
Version: 0.0.0a3
Summary: 
License: MIT
Author: acrius
Author-email: acrius@mail.ru
Requires-Python: >=3.10,<4.0
Classifier: License :: OSI Approved :: MIT License
Classifier: Programming Language :: Python :: 3
Classifier: Programming Language :: Python :: 3.10
Classifier: Programming Language :: Python :: 3.11
Requires-Dist: Jinja2 (>=3.1.2,<4.0.0)
Requires-Dist: typing-extensions (>=4.7.1,<5.0.0)
